MANIFEST.in
README.markdown
dev-requirements.txt
example_wmctrl_window_list.txt
setup.py
flitter/__init__.py
flitter/flitter.json
flitter/runraisenext.py
flitter/test_runraisenext.py
flitter/test_wmctrl.py
flitter/wmctrl.py
flitter.egg-info/PKG-INFO
flitter.egg-info/SOURCES.txt
flitter.egg-info/dependency_links.txt
flitter.egg-info/entry_points.txt
flitter.egg-info/top_level.txt