Metadata-Version: 1.1
Name: flitter
Version: 1.0.0
Summary: Fast desktop window switching and app launching utility
Home-page: https://github.com/seanh/flitter
Author: Sean Hammond
Author-email: flitter@seanh.cc
License: AGPL
Platform: UNKNOWN
Classifier: Development Status :: 4 - Beta
Classifier: License :: OSI Approved :: GNU Affero General Public License v3 or later (AGPLv3+)
Classifier: Programming Language :: Python :: 2.7
